racogpt/__init__.py
racogpt/client.py
RacoGPT-2.0.0.dist-info/LICENSE
RacoGPT-2.0.0.dist-info/METADATA
RacoGPT-2.0.0.dist-info/WHEEL
RacoGPT-2.0.0.dist-info/top_level.txt
RacoGPT-2.0.0.dist-info/RECORD
